cnside/__init__.py
cnside/authenticator/__init__.py
cnside/authenticator/auth.py
cnside/authenticator/documents.py
cnside/authenticator/server.py
cnside/cli/__init__.py
cnside/cli/api.py
cnside/cli/core.py
cnside/cli/documents.py
cnside/cli/main.py
cnside/documents/__init__.py
cnside/documents/base.py
cnside/errors/__init__.py
cnside/errors/api.py
cnside/errors/cli.py
cnside/errors/descriptors.py
cnside/metadata/__init__.py
cnside/metadata/packages.py
cnside/objects/__init__.py
cnside/objects/core.py
cnside/objects/encoders.py
cnside/parsers/__init__.py
cnside/parsers/cli_parsers.py
cnside/storage/__init__.py
cnside/storage/config.py
cnside/storage/handlers.py
cnside-0.15.6.dist-info/LICENSE.txt
cnside-0.15.6.dist-info/METADATA
cnside-0.15.6.dist-info/WHEEL
cnside-0.15.6.dist-info/entry_points.txt
cnside-0.15.6.dist-info/top_level.txt
cnside-0.15.6.dist-info/RECORD
