Metadata-Version: 2.1
Name: cnside
Version: 0.15.6
Summary: CNSIDE Command Line Interface Tool
Home-page: https://illustria.io
Author: Bogdan Kortnov
Author-email: bogdan@illustria.io
License: Proprietary
Platform: UNKNOWN
License-File: LICENSE.txt
Requires-Dist: requests (==2.26.0)
Requires-Dist: packaging (==21.0)
Requires-Dist: fastapi (==0.68.1)
Requires-Dist: uvicorn (==0.15.0)
Requires-Dist: pydantic (==1.8.2)
Requires-Dist: colorama (==0.4.4)
Requires-Dist: click (==8.0.1)
Requires-Dist: progressbar (==2.5)
